octane/__init__.py
octane/api_requestor.py
octane/error.py
octane/http_client.py
octane/multipart_data_generator.py
octane/object_classes.py
octane/octane_object.py
octane/octane_response.py
octane/request_metrics.py
octane/six.py
octane/test_data.py
octane/util.py
octane/version.py
octane/api_resources/__init__.py
octane/api_resources/customer.py
octane/api_resources/error_object.py
octane/api_resources/list_object.py
octane/api_resources/mapping.py
octane/api_resources/measurement.py
octane/api_resources/meter.py
octane/api_resources/payment_gateway_credential.py
octane/api_resources/price_list.py
octane/api_resources/price_plan.py
octane/api_resources/subscription.py
octane/api_resources/abstract/__init__.py
octane/api_resources/abstract/api_resource.py
octane/api_resources/abstract/createable_api_resource.py
octane/api_resources/abstract/custom_method.py
octane/api_resources/abstract/deletable_api_resource.py
octane/api_resources/abstract/listable_api_resource.py
octane/api_resources/abstract/nested_resource_class_methods.py
octane/api_resources/abstract/singleton_api_resource.py
octane/api_resources/abstract/updateable_api_resource.py
octane/api_resources/abstract/verify_mixin.py
octane/data/ca-certificates.crt
octane-1.0.11.dist-info/LICENSE
octane-1.0.11.dist-info/METADATA
octane-1.0.11.dist-info/WHEEL
octane-1.0.11.dist-info/top_level.txt
octane-1.0.11.dist-info/RECORD
